neko_rexec/__init__.py
neko_rexec/__main__.py
neko_rexec/send_remote_cmd.py
neko_rexec-0.0.4.dist-info/LICENSE
neko_rexec-0.0.4.dist-info/METADATA
neko_rexec-0.0.4.dist-info/WHEEL
neko_rexec-0.0.4.dist-info/top_level.txt
neko_rexec-0.0.4.dist-info/RECORD
