Metadata-Version: 2.1
Name: neko_rexec
Version: 0.0.4
Summary: send remote command through paramiko via ssh.
Author-email: GGN_2015 <premierbob@qq.com>
License: MIT License
Requires-Python: >=3.10
License-File: LICENSE
Requires-Dist: paramiko
